pkgutil.py
setup.py
micropython_pkgutil.egg-info/PKG-INFO
micropython_pkgutil.egg-info/SOURCES.txt
micropython_pkgutil.egg-info/dependency_links.txt
micropython_pkgutil.egg-info/requires.txt
micropython_pkgutil.egg-info/top_level.txt